stocktown/__init__.py
stocktown/caches.py
stocktown/chart.py
stocktown/client.py
stocktown/enums.py
stocktown/filters.py
stocktown/language.py
stocktown/scorer.py
stocktown/stock.py
stocktown/tools.py
stocktown-0.1.202103171133.dist-info/METADATA
stocktown-0.1.202103171133.dist-info/WHEEL
stocktown-0.1.202103171133.dist-info/top_level.txt
stocktown-0.1.202103171133.dist-info/RECORD
