Metadata-Version: 2.1
Name: stocktown
Version: 0.1.202103171133
Summary: UNKNOWN
Home-page: UNKNOWN
Author: Sikoo Lee
Author-email: 
License: UNKNOWN
Project-URL: Documentation, https://stocktown.readthedocs.io
Project-URL: Source, https://github.com/zhangheli/stocktown
Platform: UNKNOWN
Classifier: Development Status :: 5 - Production/Stable
Classifier: Intended Audience :: Developers
Classifier: Natural Language :: English
Classifier: License :: OSI Approved :: Apache Software License
Classifier: Programming Language :: Python
Classifier: Programming Language :: Python :: 2
Classifier: Programming Language :: Python :: 2.7
Classifier: Programming Language :: Python :: 3
Classifier: Programming Language :: Python :: 3.5
Classifier: Programming Language :: Python :: 3.6
Classifier: Programming Language :: Python :: 3.7
Classifier: Programming Language :: Python :: 3.8
Classifier: Programming Language :: Python :: 3.9
Classifier: Programming Language :: Python :: Implementation :: CPython
Classifier: Programming Language :: Python :: Implementation :: PyPy
Requires-Python: >3.5, !=3.0.*, !=3.1.*, !=3.2.*, !=3.3.*, !=3.4.*
Requires-Dist: cacheout
Requires-Dist: pandas
Requires-Dist: requests
Requires-Dist: seaborn
Requires-Dist: mplfinance
Requires-Dist: pandas-datareader
Requires-Dist: plotly
